perceptron/Perceptron.py
perceptron/__init__.py
Mypackage_pkg_VeluruBhanuprakash-0.0.2.dist-info/LICENSE
Mypackage_pkg_VeluruBhanuprakash-0.0.2.dist-info/METADATA
Mypackage_pkg_VeluruBhanuprakash-0.0.2.dist-info/WHEEL
Mypackage_pkg_VeluruBhanuprakash-0.0.2.dist-info/top_level.txt
Mypackage_pkg_VeluruBhanuprakash-0.0.2.dist-info/RECORD
